
using System;
namespace Dot42.JvmClassLib.Bytecode
{
    partial class CodeNames
    {
        internal static readonly Tuple<int, string>[] Names = new[] { Tuple.Create(0, "NOP"),
Tuple.Create(1, "ACONST_NULL"),
Tuple.Create(2, "ICONST_M1"),
Tuple.Create(3, "ICONST_0"),
Tuple.Create(4, "ICONST_1"),
Tuple.Create(5, "ICONST_2"),
Tuple.Create(6, "ICONST_3"),
Tuple.Create(7, "ICONST_4"),
Tuple.Create(8, "ICONST_5"),
Tuple.Create(9, "LCONST_0"),
Tuple.Create(10, "LCONST_1"),
Tuple.Create(11, "FCONST_0"),
Tuple.Create(12, "FCONST_1"),
Tuple.Create(13, "FCONST_2"),
Tuple.Create(14, "DCONST_0"),
Tuple.Create(15, "DCONST_1"),
Tuple.Create(16, "BIPUSH"),
Tuple.Create(17, "SIPUSH"),
Tuple.Create(18, "LDC"),
Tuple.Create(19, "LDC_W"),
Tuple.Create(20, "LDC2_W"),
Tuple.Create(21, "ILOAD"),
Tuple.Create(22, "LLOAD"),
Tuple.Create(23, "FLOAD"),
Tuple.Create(24, "DLOAD"),
Tuple.Create(25, "ALOAD"),
Tuple.Create(26, "ILOAD_0"),
Tuple.Create(27, "ILOAD_1"),
Tuple.Create(28, "ILOAD_2"),
Tuple.Create(29, "ILOAD_3"),
Tuple.Create(30, "LLOAD_0"),
Tuple.Create(31, "LLOAD_1"),
Tuple.Create(32, "LLOAD_2"),
Tuple.Create(33, "LLOAD_3"),
Tuple.Create(34, "FLOAD_0"),
Tuple.Create(35, "FLOAD_1"),
Tuple.Create(36, "FLOAD_2"),
Tuple.Create(37, "FLOAD_3"),
Tuple.Create(38, "DLOAD_0"),
Tuple.Create(39, "DLOAD_1"),
Tuple.Create(40, "DLOAD_2"),
Tuple.Create(41, "DLOAD_3"),
Tuple.Create(42, "ALOAD_0"),
Tuple.Create(43, "ALOAD_1"),
Tuple.Create(44, "ALOAD_2"),
Tuple.Create(45, "ALOAD_3"),
Tuple.Create(46, "IALOAD"),
Tuple.Create(47, "LALOAD"),
Tuple.Create(48, "FALOAD"),
Tuple.Create(49, "DALOAD"),
Tuple.Create(50, "AALOAD"),
Tuple.Create(51, "BALOAD"),
Tuple.Create(52, "CALOAD"),
Tuple.Create(53, "SALOAD"),
Tuple.Create(54, "ISTORE"),
Tuple.Create(55, "LSTORE"),
Tuple.Create(56, "FSTORE"),
Tuple.Create(57, "DSTORE"),
Tuple.Create(58, "ASTORE"),
Tuple.Create(59, "ISTORE_0"),
Tuple.Create(60, "ISTORE_1"),
Tuple.Create(61, "ISTORE_2"),
Tuple.Create(62, "ISTORE_3"),
Tuple.Create(63, "LSTORE_0"),
Tuple.Create(64, "LSTORE_1"),
Tuple.Create(65, "LSTORE_2"),
Tuple.Create(66, "LSTORE_3"),
Tuple.Create(67, "FSTORE_0"),
Tuple.Create(68, "FSTORE_1"),
Tuple.Create(69, "FSTORE_2"),
Tuple.Create(70, "FSTORE_3"),
Tuple.Create(71, "DSTORE_0"),
Tuple.Create(72, "DSTORE_1"),
Tuple.Create(73, "DSTORE_2"),
Tuple.Create(74, "DSTORE_3"),
Tuple.Create(75, "ASTORE_0"),
Tuple.Create(76, "ASTORE_1"),
Tuple.Create(77, "ASTORE_2"),
Tuple.Create(78, "ASTORE_3"),
Tuple.Create(79, "IASTORE"),
Tuple.Create(80, "LASTORE"),
Tuple.Create(81, "FASTORE"),
Tuple.Create(82, "DASTORE"),
Tuple.Create(83, "AASTORE"),
Tuple.Create(84, "BASTORE"),
Tuple.Create(85, "CASTORE"),
Tuple.Create(86, "SASTORE"),
Tuple.Create(87, "POP"),
Tuple.Create(88, "POP2"),
Tuple.Create(89, "DUP"),
Tuple.Create(90, "DUP_X1"),
Tuple.Create(91, "DUP_X2"),
Tuple.Create(92, "DUP2"),
Tuple.Create(93, "DUP2_X1"),
Tuple.Create(94, "DUP2_X2"),
Tuple.Create(95, "SWAP"),
Tuple.Create(96, "IADD"),
Tuple.Create(97, "LADD"),
Tuple.Create(98, "FADD"),
Tuple.Create(99, "DADD"),
Tuple.Create(100, "ISUB"),
Tuple.Create(101, "LSUB"),
Tuple.Create(102, "FSUB"),
Tuple.Create(103, "DSUB"),
Tuple.Create(104, "IMUL"),
Tuple.Create(105, "LMUL"),
Tuple.Create(106, "FMUL"),
Tuple.Create(107, "DMUL"),
Tuple.Create(108, "IDIV"),
Tuple.Create(109, "LDIV"),
Tuple.Create(110, "FDIV"),
Tuple.Create(111, "DDIV"),
Tuple.Create(112, "IREM"),
Tuple.Create(113, "LREM"),
Tuple.Create(114, "FREM"),
Tuple.Create(115, "DREM"),
Tuple.Create(116, "INEG"),
Tuple.Create(117, "LNEG"),
Tuple.Create(118, "FNEG"),
Tuple.Create(119, "DNEG"),
Tuple.Create(120, "ISHL"),
Tuple.Create(121, "LSHL"),
Tuple.Create(122, "ISHR"),
Tuple.Create(123, "LSHR"),
Tuple.Create(124, "IUSHR"),
Tuple.Create(125, "LUSHR"),
Tuple.Create(126, "IAND"),
Tuple.Create(127, "LAND"),
Tuple.Create(128, "IOR"),
Tuple.Create(129, "LOR"),
Tuple.Create(130, "IXOR"),
Tuple.Create(131, "LXOR"),
Tuple.Create(132, "IINC"),
Tuple.Create(133, "I2L"),
Tuple.Create(134, "I2F"),
Tuple.Create(135, "I2D"),
Tuple.Create(136, "L2I"),
Tuple.Create(137, "L2F"),
Tuple.Create(138, "L2D"),
Tuple.Create(139, "F2I"),
Tuple.Create(140, "F2L"),
Tuple.Create(141, "F2D"),
Tuple.Create(142, "D2I"),
Tuple.Create(143, "D2L"),
Tuple.Create(144, "D2F"),
Tuple.Create(145, "I2B"),
Tuple.Create(146, "I2C"),
Tuple.Create(147, "I2S"),
Tuple.Create(148, "LCMP"),
Tuple.Create(149, "FCMPL"),
Tuple.Create(150, "FCMPG"),
Tuple.Create(151, "DCMPL"),
Tuple.Create(152, "DCMPG"),
Tuple.Create(153, "IFEQ"),
Tuple.Create(154, "IFNE"),
Tuple.Create(155, "IFLT"),
Tuple.Create(156, "IFGE"),
Tuple.Create(157, "IFGT"),
Tuple.Create(158, "IFLE"),
Tuple.Create(159, "IF_ICMPEQ"),
Tuple.Create(160, "IF_ICMPNE"),
Tuple.Create(161, "IF_ICMPLT"),
Tuple.Create(162, "IF_ICMPGE"),
Tuple.Create(163, "IF_ICMPGT"),
Tuple.Create(164, "IF_ICMPLE"),
Tuple.Create(165, "IF_ACMPEQ"),
Tuple.Create(166, "IF_ACMPNE"),
Tuple.Create(167, "GOTO"),
Tuple.Create(168, "JSR"),
Tuple.Create(169, "RET"),
Tuple.Create(170, "TABLESWITCH"),
Tuple.Create(171, "LOOKUPSWITCH"),
Tuple.Create(172, "IRETURN"),
Tuple.Create(173, "LRETURN"),
Tuple.Create(174, "FRETURN"),
Tuple.Create(175, "DRETURN"),
Tuple.Create(176, "ARETURN"),
Tuple.Create(177, "RETURN"),
Tuple.Create(178, "GETSTATIC"),
Tuple.Create(179, "PUTSTATIC"),
Tuple.Create(180, "GETFIELD"),
Tuple.Create(181, "PUTFIELD"),
Tuple.Create(182, "INVOKEVIRTUAL"),
Tuple.Create(183, "INVOKESPECIAL"),
Tuple.Create(184, "INVOKESTATIC"),
Tuple.Create(185, "INVOKEINTERFACE"),
Tuple.Create(187, "NEW"),
Tuple.Create(188, "NEWARRAY"),
Tuple.Create(189, "ANEWARRAY"),
Tuple.Create(190, "ARRAYLENGTH"),
Tuple.Create(191, "ATHROW"),
Tuple.Create(192, "CHECKCAST"),
Tuple.Create(193, "INSTANCEOF"),
Tuple.Create(194, "MONITORENTER"),
Tuple.Create(195, "MONITOREXIT"),
Tuple.Create(196, "WIDE"),
Tuple.Create(197, "MULTIANEWARRAY"),
Tuple.Create(198, "IFNULL"),
Tuple.Create(199, "IFNONNULL"),
Tuple.Create(200, "GOTO_W"),
Tuple.Create(201, "JSR_W") };
    }
}